azure/storage/filedatalake/__init__.py
azure/storage/filedatalake/_data_lake_directory_client.py
azure/storage/filedatalake/_data_lake_file_client.py
azure/storage/filedatalake/_data_lake_lease.py
azure/storage/filedatalake/_data_lake_service_client.py
azure/storage/filedatalake/_deserialize.py
azure/storage/filedatalake/_download.py
azure/storage/filedatalake/_file_system_client.py
azure/storage/filedatalake/_list_paths_helper.py
azure/storage/filedatalake/_models.py
azure/storage/filedatalake/_path_client.py
azure/storage/filedatalake/_quick_query_helper.py
azure/storage/filedatalake/_serialize.py
azure/storage/filedatalake/_shared_access_signature.py
azure/storage/filedatalake/_upload_helper.py
azure/storage/filedatalake/_version.py
azure/storage/filedatalake/py.typed
azure/storage/filedatalake/_generated/__init__.py
azure/storage/filedatalake/_generated/_azure_data_lake_storage_restapi.py
azure/storage/filedatalake/_generated/_configuration.py
azure/storage/filedatalake/_generated/_patch.py
azure/storage/filedatalake/_generated/_serialization.py
azure/storage/filedatalake/_generated/py.typed
azure/storage/filedatalake/_generated/aio/__init__.py
azure/storage/filedatalake/_generated/aio/_azure_data_lake_storage_restapi.py
azure/storage/filedatalake/_generated/aio/_configuration.py
azure/storage/filedatalake/_generated/aio/_patch.py
azure/storage/filedatalake/_generated/aio/operations/__init__.py
azure/storage/filedatalake/_generated/aio/operations/_file_system_operations.py
azure/storage/filedatalake/_generated/aio/operations/_patch.py
azure/storage/filedatalake/_generated/aio/operations/_path_operations.py
azure/storage/filedatalake/_generated/aio/operations/_service_operations.py
azure/storage/filedatalake/_generated/models/__init__.py
azure/storage/filedatalake/_generated/models/_azure_data_lake_storage_restapi_enums.py
azure/storage/filedatalake/_generated/models/_models_py3.py
azure/storage/filedatalake/_generated/models/_patch.py
azure_storage_file_datalake-12.19.0.dist-info/LICENSE
azure_storage_file_datalake-12.19.0.dist-info/METADATA
azure_storage_file_datalake-12.19.0.dist-info/WHEEL
azure_storage_file_datalake-12.19.0.dist-info/top_level.txt
azure_storage_file_datalake-12.19.0.dist-info/RECORD
