Metadata-Version: 2.1
Name: azure-storage-file-datalake
Version: 12.19.0
Summary: Microsoft Azure File DataLake Storage Client Library for Python
Home-page: https://github.com/Azure/azure-sdk-for-python
Author: Microsoft Corporation
Author-email: ascl@microsoft.com
License: MIT License
Keywords: azure,azure sdk
Classifier: Development Status :: 5 - Production/Stable
Classifier: Programming Language :: Python
Classifier: Programming Language :: Python :: 3 :: Only
Classifier: Programming Language :: Python :: 3
Classifier: Programming Language :: Python :: 3.8
Classifier: Programming Language :: Python :: 3.9
Classifier: Programming Language :: Python :: 3.10
Classifier: Programming Language :: Python :: 3.11
Classifier: Programming Language :: Python :: 3.12
Classifier: License :: OSI Approved :: MIT License
Requires-Python: >=3.8
License-File: LICENSE
Requires-Dist: azure-core >=1.30.0
Requires-Dist: azure-storage-blob >=12.25.0
Requires-Dist: typing-extensions >=4.6.0
Requires-Dist: isodate >=0.6.1
Provides-Extra: aio
Requires-Dist: azure-core[aio] >=1.30.0 ; extra == 'aio'
